{"title":"Hexo","subtitle":"","description":"","author":"John Doe","language":"en","timezone":"","url":"http://example.com","root":"/","permalink":"/post/:title.html","permalink_defaults":null,"pretty_urls":{"trailing_index":true,"trailing_html":true},"source_dir":"source","public_dir":"public","tag_dir":"tags","archive_dir":"archives","category_dir":"categories","code_dir":"downloads/code","i18n_dir":":lang","skip_render":null,"new_post_name":":title.md","default_layout":"post","titlecase":false,"external_link":{"enable":true,"field":"site","exclude":""},"filename_case":0,"render_drafts":false,"post_asset_folder":false,"relative_link":false,"future":true,"highlight":{"enable":true,"auto_detect":false,"line_number":true,"tab_replace":"","wrap":true,"hljs":false},"prismjs":{"enable":false,"preprocess":true,"line_number":true,"tab_replace":""},"default_category":"uncategorized","category_map":null,"tag_map":null,"date_format":"YYYY-MM-DD","time_format":"HH:mm:ss","updated_option":"mtime","per_page":10,"pagination_dir":"page","theme":"aurora","server":{"port":4000,"log":false,"compress":false,"header":true,"cache":false},"deploy":{"type":"git","repo":"https://github.com/wakkana/wakkana.github.io.git","branch":"master"},"ignore":null,"meta_generator":true,"keywords":null,"index_generator":{"per_page":10,"order_by":"-date","path":""},"include":null,"exclude":null,"live2d":{"enable":true,"scriptFrom":"local","pluginModelPath":"assets/","model":{"use":"live2d-widget-model-tororo"},"hHeadPos":0.5,"vHeadPos":0.618,"display":{"superSample":2,"width":250,"height":500,"position":"right","hOffset":0,"vOffset":-100},"mobile":{"show":false,"scale":0.5},"react":{"opacityDefault":0.7,"opacityOnHover":0.2}},"archive_generator":{"per_page":10,"yearly":true,"monthly":true,"daily":false},"category_generator":{"per_page":10},"marked":{"gfm":true,"pedantic":false,"breaks":true,"smartLists":true,"smartypants":true,"modifyAnchors":0,"autolink":true,"mangle":true,"sanitizeUrl":false,"headerIds":true,"anchorAlias":false,"lazyload":false,"prependRoot":false,"postAsset":false,"external_link":{"enable":false,"exclude":[],"nofollow":false},"descriptionLists":true},"tag_generator":{"per_page":10},"theme_config":{"site":{"subtitle":"Wakkana's Hiddenpalace","author":"Wakkana","nick":"　","description":"boring man","language":"cn","multi_language":true,"logo":"https://img-blog.csdnimg.cn/20210313122054101.png","avatar":"file/mypic.jpg","beian":""},"authors":{"tom":{"name":"Tom Cat","avatar":"https://img-blog.csdnimg.cn/20210313122054101.png","link":"https://github.com/TriDiamond"}},"menu":{"About":false,"Tags":true,"Archives":true,"resources":{"name":"Resources","i18n":"resources","path":"/page/resources"},"weibo":{"name":"Weibo","i18n":"weibo","path":"https://weibo.com/6962193334/profile?rightmod=1&wvr=6&mod=personinfo"}},"theme":{"dark_mode":true,"gradient":{"color_1":"#ffc1cf","color_2":"#e8ffb7","color_3":"#e2a0ff"}},"socials":{"github":"https://github.com/wakkana","twitter":"","stackoverflow":""},"site_meta":{"cdn":"en"},"gitalk":{"enable":true,"autoExpand":true,"clientID":"","clientSecret":"","repo":"dev-blog-comments","owner":"Wakkana","admin":["Wakkana"],"id":"uid","language":"en","distractionFreeMode":true,"recentComment":true},"valine":{"enable":false,"app_id":null,"app_key":null,"avatar":"","placeholder":"Leave your thoughts behind~","visitor":true,"lang":"en","meta":["nick","mail"],"admin":"TriDiamond","recentComment":true},"busuanzi":{"enable":true},"version":"1.0.1"}}